ecbundle/__init__.py
ecbundle/build.py
ecbundle/bundle.py
ecbundle/create.py
ecbundle/data.py
ecbundle/download.py
ecbundle/git.py
ecbundle/logging.py
ecbundle/option.py
ecbundle/parse.py
ecbundle/populate.py
ecbundle/project.py
ecbundle/util.py
ecbundle-2.3.0.data/scripts/ecbundle
ecbundle-2.3.0.data/scripts/ecbundle-build
ecbundle-2.3.0.data/scripts/ecbundle-create
ecbundle-2.3.0.data/scripts/ecbundle-version
ecbundle-2.3.0.dist-info/licenses/LICENSE
ecbundle-2.3.0.dist-info/METADATA
ecbundle-2.3.0.dist-info/WHEEL
ecbundle-2.3.0.dist-info/top_level.txt
ecbundle-2.3.0.dist-info/zip-safe
ecbundle-2.3.0.dist-info/RECORD
