Metadata-Version: 2.4
Name: ecbundle
Version: 2.3.0
Summary: Bundle management tool for CMake projects
Author: European Centre for Medium-Range Weather Forecasts (ECMWF)
Author-email: software.support@ecmwf.int
Keywords: tool
License-File: LICENSE
Requires-Dist: ruamel.yaml
Requires-Dist: pathlib
Dynamic: author
Dynamic: author-email
Dynamic: description
Dynamic: description-content-type
Dynamic: keywords
Dynamic: license-file
Dynamic: requires-dist
Dynamic: summary
